{
  "schemaVersion": "1.0",
  "server": {
    "name": "mcp-server-vibes-coded",
    "displayName": "Vibes-Coded Agent Tools",
    "description": "MCP server exposing Vibes-Coded's pay-per-call x402 agent-tool endpoints (agent-reliability guards, memory integrity, cost control, supply-chain trust, and utilities) as discoverable MCP tools. Agents discover tools here, then call them; paid calls settle USDC via the Coinbase x402 facilitator.",
    "version": "1.0.1",
    "license": "MIT",
    "homepage": "https://vibes-coded.com",
    "repository": "https://github.com/doteyeso-ops/mcp-server-vibes-coded",
    "documentation": "https://vibes-coded.com/api/v1/outcomes/meta",
    "category": "developer-tools",
    "tags": [
      "x402",
      "pay-per-call",
      "agents",
      "solana",
      "usdc",
      "reliability",
      "agent-tools"
    ]
  }
}
